setup.py
satchmo_braintree/__init__.py
satchmo_braintree/config.py
satchmo_braintree/models.py
satchmo_braintree/processor.py
satchmo_braintree/urls.py
satchmo_braintree/views.py
satchmo_braintree.egg-info/PKG-INFO
satchmo_braintree.egg-info/SOURCES.txt
satchmo_braintree.egg-info/dependency_links.txt
satchmo_braintree.egg-info/not-zip-safe
satchmo_braintree.egg-info/requires.txt
satchmo_braintree.egg-info/top_level.txt