Metadata-Version: 1.0
Name: satchmo-braintree
Version: 0.2
Summary: An easy way to integrate Satchmo checkout with Braintree Payment Solutions gateway.
Home-page: http://github.com/tivix/satchmo-braintree
Author: Sumit Chachra
Author-email: chachra@tivix.com
License: UNKNOWN
Platform: UNKNOWN
Classifier: Framework :: Django
Classifier: Intended Audience :: Developers
Classifier: Intended Audience :: System Administrators
Classifier: Operating System :: OS Independent
Classifier: Topic :: Software Development
